{"url":"https://brasilescola.uol.com.br/historiab/guerra-contestado.htm","contentTitle":"Guerra do Contestado","originalContent":"Ao longo de sua História a região do Contestado foi alvo de sucessivos episódios de disputa política e econômica. Localizada entre os estados do Paraná e Santa Catarina, a região foi marcada por essas disputas em razão da presença de uma rica floresta e uma grande região dedicada à plantação de erva-mate. Uma das mais imediatas manifestações desse problema se dava na pressão exercida pelos grandes proprietários de terra que forçavam agregados e posseiros a se estabelecerem em outras terras.\n\nAlém disso, a construção de uma estrada de ferro interligando os estados de São Paulo e Rio Grande do Sul agravou o problema social ali instalado. Sob a liderança do empresário estadunidense Percival Farquhar, a Brazil Railway Company comprou uma extensa área para construção desta estrada, onde diversas famílias já estavam instaladas. Após viabilizar o processo de desocupação das terras, a companhia atraiu a mão-de-obra de mais de 8 mil operários que participaram da gigantesca obra.\n\nDepois de realizar a construção, a Brazil Railway adquiriu uma outra área com mais de 180 mil hectares onde realizaria exploração madeireira. Utilizando um moderno maquinário para a execução desse novo empreendimento, a empresa estrangeira precisou de um contingente mínimo de mão-de-obra, o que acabou forçando a expulsão de outra leva de pequenos agricultores que também estavam fixados naquela região.\n\nCom a formação dessa massa de operários desempregados e camponeses desapropriados, a região do Contestado começou a presenciar um movimento messiânico. Diversos profetas, beatos e “monges” apareceram pregando ideais de justiça, paz e comunhão que seriam estabelecidos em um movimento de inspiração religiosa. O primeiro desses líderes foi o beato José Maria, que atacava o autoritarismo da ordem republicana e pregava novos tempos de prosperidade e comunhão espiritual.\n\nInspirado pela lenda messiânica do antigo rei português Dom Sebastião, José Maria agrupou diversos seguidores para a fundação da comunidade de Quadrado Santo, que viveu da agricultura subsistente e do furto de gado. Preocupados com a formação de comunidades desse mesmo tipo, os governos estadual e federal passaram a enviar expedições militares contra a população de Quadrado Santo. Ao saberem da ação do governo, os sertanejos fugiram para a cidade de Faxinal do Irani, no Paraná.\n\nApós essa fuga, ainda no ano de 1912, um novo destacamento militar foi mandado para entrar em confronto com os seguidores de José Maria. Durante os conflitos, as tropas federais foram derrotadas, entretanto o líder espiritual acabou morrendo. Após esse primeiro confronto, os rebeldes começaram a reorganizar a comunidade de Quadrado Santo. No final do ano seguinte, uma nova luta foi travada com os militares e, mais uma vez, a comunidade do Contestado subjugou as autoridades republicanas.\n\nEm 1914, o governo mais uma vez foi neutralizado com a fuga em massa dos moradores do contestado. No ano seguinte, outros confrontos seriam marcados com sucessivas derrotas do Exército. O já prolongado conflito só veio a ter um fim quando as tropas do governo foram mantidas por mais de um ano em confrontos regulares contra a comunidade revoltosa. Para tanto, utilizaram de aviões e uma pesada artilharia. No fim da luta, em 1916, milhares de sertanejos foram brutalmente executados.Por Rainer Sousa\nGraduado em História\nEquipe Brasil EscolaRebeliões na República Velha - Brasil República\nHistória do Brasil - Brasil Escola\n                                                Gostaria de fazer a referência deste texto em um trabalho escolar ou acadêmico? Veja:\n                                            \n                                                SOUSA, Rainer Gonçalves.\n                                                \"Guerra do Contestado\"; Brasil Escola. \n                                                Disponível em: https://brasilescola.uol.com.br/historiab/guerra-contestado.htm. Acesso em 28 de maio \n                                                de 2020.","referenceUrls":[],"contentSanitized":"Ao longo de sua História a região do Contestado foi alvo de sucessivos episódios de disputa política e econômica. Localizada entre os estados do Paraná e Santa Catarina, a região foi marcada por essas disputas em razão da presença de uma rica floresta e uma grande região dedicada à plantação de erva-mate. Uma das mais imediatas manifestações desse problema se dava na pressão exercida pelos grandes proprietários de terra que forçavam agregados e posseiros a se estabelecerem em outras terras. Além disso, a construção de uma estrada de ferro interligando os estados de São Paulo e Rio Grande do Sul agravou o problema social ali instalado. Sob a liderança do empresário estadunidense Percival Farquhar, a Brazil Railway Company comprou uma extensa área para construção desta estrada, onde diversas famílias já estavam instaladas. Após viabilizar o processo de desocupação das terras, a companhia atraiu a mão-de-obra de mais de 8 mil operários que participaram da gigantesca obra. Depois de realizar a construção, a Brazil Railway adquiriu uma outra área com mais de 180 mil hectares onde realizaria exploração madeireira. Utilizando um moderno maquinário para a execução desse novo empreendimento, a empresa estrangeira precisou de um contingente mínimo de mão-de-obra, o que acabou forçando a expulsão de outra leva de pequenos agricultores que também estavam fixados naquela região. Com a formação dessa massa de operários desempregados e camponeses desapropriados, a região do Contestado começou a presenciar um movimento messiânico. Diversos profetas, beatos e “monges” apareceram pregando ideais de justiça, paz e comunhão que seriam estabelecidos em um movimento de inspiração religiosa. O primeiro desses líderes foi o beato José Maria, que atacava o autoritarismo da ordem republicana e pregava novos tempos de prosperidade e comunhão espiritual. Inspirado pela lenda messiânica do antigo rei português Dom Sebastião, José Maria agrupou diversos seguidores para a fundação da comunidade de Quadrado Santo, que viveu da agricultura subsistente e do furto de gado. Preocupados com a formação de comunidades desse mesmo tipo, os governos estadual e federal passaram a enviar expedições militares contra a população de Quadrado Santo. Ao saberem da ação do governo, os sertanejos fugiram para a cidade de Faxinal do Irani, no Paraná. Após essa fuga, ainda no ano de 1912, um novo destacamento militar foi mandado para entrar em confronto com os seguidores de José Maria. Durante os conflitos, as tropas federais foram derrotadas, entretanto o líder espiritual acabou morrendo. Após esse primeiro confronto, os rebeldes começaram a reorganizar a comunidade de Quadrado Santo. No final do ano seguinte, uma nova luta foi travada com os militares e, mais uma vez, a comunidade do Contestado subjugou as autoridades republicanas. Em 1914, o governo mais uma vez foi neutralizado com a fuga em massa dos moradores do contestado. No ano seguinte, outros confrontos seriam marcados com sucessivas derrotas do Exército. O já prolongado conflito só veio a ter um fim quando as tropas do governo foram mantidas por mais de um ano em confrontos regulares contra a comunidade revoltosa. Para tanto, utilizaram de aviões e uma pesada artilharia. No fim da luta, em 1916, milhares de sertanejos foram brutalmente executados.Por Rainer Sousa Graduado em História Equipe Brasil EscolaRebeliões na República Velha - Brasil República História do Brasil - Brasil Escola                                                 Gostaria de fazer a referência deste texto em um trabalho escolar ou acadêmico? Veja:                                                 SOUSA, Rainer Gonçalves.                                                 \"Guerra do Contestado\"; Brasil Escola.                                                  Disponível em: https://brasilescola.uol.com.br/historiab/guerra-contestado.htm. Acesso em 28 de maio                                                  de 2020.","sentences":[{"text":"Ao longo de sua História a região do Contestado foi alvo de sucessivos episódios de disputa política e econômica.","keywords":["longo de sua História","região do Contestado"],"locations":[],"dates":null},{"text":"Localizada entre os estados do Paraná e Santa Catarina, a região foi marcada por essas disputas em razão da presença de uma rica floresta e uma grande região dedicada à plantação de erva-mate.","keywords":["estados do Paraná","Santa Catarina"],"locations":[{"city":null,"state":"Parana","country":"BR","loc":{"type":"Point","coordinates":[-24.4842187,-51.8148872]}},{"city":null,"state":"Santa Catarina","country":"BR","loc":{"type":"Point","coordinates":[-27.0628367,-51.114965]}}],"dates":null},{"text":"Uma das mais imediatas manifestações desse problema se dava na pressão exercida pelos grandes proprietários de terra que forçavam agregados e posseiros a se estabelecerem em outras terras.","keywords":["imediatas manifestações","grandes proprietários de terra"],"locations":[],"dates":null},{"text":"Além disso, a construção de uma estrada de ferro interligando os estados de São Paulo e Rio Grande do Sul agravou o problema social ali instalado.","keywords":["construção de uma estrada de ferro","estados de São Paulo"],"locations":[{"city":"Rio Grande","state":"Tierra del Fuego","country":"BR","loc":{"type":"Point","coordinates":[-52.09861,-32.035]}},{"city":null,"state":"Rio Grande do Sul","country":"BR","loc":{"type":"Point","coordinates":[-29.8425284,-53.7680577]}},{"city":null,"state":"Sao Paulo","country":"BR","loc":{"type":"Point","coordinates":[-21.9549806,-49.0232348]}}],"dates":null},{"text":"Sob a liderança do empresário estadunidense Percival Farquhar, a Brazil Railway Company comprou uma extensa área para construção desta estrada, onde diversas famílias já estavam instaladas.","keywords":["liderança do empresário estadunidense","Brazil Railway Company"],"locations":[],"dates":null},{"text":"Após viabilizar o processo de desocupação das terras, a companhia atraiu a mão-de-obra de mais de 8 mil operários que participaram da gigantesca obra.","keywords":["processo de desocupação das terras","gigantesca obra"],"locations":[],"dates":null},{"text":"Depois de realizar a construção, a Brazil Railway adquiriu uma outra área com mais de 180 mil hectares onde realizaria exploração madeireira.","keywords":["Brazil Railway","construção"],"locations":[],"dates":null},{"text":"Utilizando um moderno maquinário para a execução desse novo empreendimento, a empresa estrangeira precisou de um contingente mínimo de mão-de-obra, o que acabou forçando a expulsão de outra leva de pequenos agricultores que também estavam fixados naquela região.","keywords":["moderno maquinário","novo empreendimento"],"locations":[],"dates":null},{"text":"Com a formação dessa massa de operários desempregados e camponeses desapropriados, a região do Contestado começou a presenciar um movimento messiânico.","keywords":["massa de operários desempregados","camponeses desapropriados"],"locations":[],"dates":null},{"text":"Diversos profetas, beatos e “monges” apareceram pregando ideais de justiça, paz e comunhão que seriam estabelecidos em um movimento de inspiração religiosa.","keywords":["ideais de justiça","movimento de inspiração religiosa"],"locations":[],"dates":null},{"text":"O primeiro desses líderes foi o beato José Maria, que atacava o autoritarismo da ordem republicana e pregava novos tempos de prosperidade e comunhão espiritual.","keywords":["beato José Maria","autoritarismo da ordem republicana"],"locations":[],"dates":null},{"text":"Inspirado pela lenda messiânica do antigo rei português Dom Sebastião, José Maria agrupou diversos seguidores para a fundação da comunidade de Quadrado Santo, que viveu da agricultura subsistente e do furto de gado.","keywords":["Dom Sebastião","José Maria"],"locations":[],"dates":null},{"text":"Preocupados com a formação de comunidades desse mesmo tipo, os governos estadual e federal passaram a enviar expedições militares contra a população de Quadrado Santo.","keywords":["formação de comunidades","governos estadual"],"locations":[],"dates":null},{"text":"Ao saberem da ação do governo, os sertanejos fugiram para a cidade de Faxinal do Irani, no Paraná.","keywords":["ação do governo","cidade de Faxinal do Irani"],"locations":[{"city":"Faxinal","state":"Paraná","country":"BR","loc":{"type":"Point","coordinates":[-51.31944,-24.00028]}}],"dates":null},{"text":"Após essa fuga, ainda no ano de 1912, um novo destacamento militar foi mandado para entrar em confronto com os seguidores de José Maria.","keywords":["no ano","novo destacamento militar"],"locations":[],"dates":["1912"]},{"text":"Durante os conflitos, as tropas federais foram derrotadas, entretanto o líder espiritual acabou morrendo.","keywords":["tropas federais","líder espiritual"],"locations":[],"dates":null},{"text":"Após esse primeiro confronto, os rebeldes começaram a reorganizar a comunidade de Quadrado Santo.","keywords":["primeiro confronto","comunidade de Quadrado Santo"],"locations":[],"dates":null},{"text":"No final do ano seguinte, uma nova luta foi travada com os militares e, mais uma vez, a comunidade do Contestado subjugou as autoridades republicanas.","keywords":["ano seguinte","nova luta"],"locations":[],"dates":null},{"text":"Em 1914, o governo mais uma vez foi neutralizado com a fuga em massa dos moradores do contestado.","keywords":["massa dos moradores","governo"],"locations":[],"dates":["1914"]},{"text":"No ano seguinte, outros confrontos seriam marcados com sucessivas derrotas do Exército.","keywords":["ano seguinte","sucessivas derrotas do Exército"],"locations":[],"dates":null},{"text":"O já prolongado conflito só veio a ter um fim quando as tropas do governo foram mantidas por mais de um ano em confrontos regulares contra a comunidade revoltosa.","keywords":["prolongado conflito","tropas do governo"],"locations":[],"dates":null},{"text":"Para tanto, utilizaram de aviões e uma pesada artilharia.","keywords":["pesada artilharia","aviões"],"locations":[],"dates":null},{"text":"No fim da luta, em 1916, milhares de sertanejos foram brutalmente executados","keywords":["fim da luta","milhares de sertanejos"],"locations":[],"dates":["1916"]},{"text":"Por Rainer Sousa Graduado em História Equipe Brasil EscolaRebeliões na República Velha - Brasil República História do Brasil - Brasil Escola Gostaria de fazer a referência deste texto em um trabalho escolar ou acadêmico?","keywords":["Rainer Sousa Graduado","Brasil Escola Gostaria"],"locations":[{"city":"Sousa","state":"Paraíba","country":"BR","loc":{"type":"Point","coordinates":[-38.22806,-6.75917]}}],"dates":null},{"text":"Veja: SOUSA, Rainer Gonçalves.","keywords":["Rainer Gonçalves","SOUSA"],"locations":[],"dates":null},{"text":"\"Guerra do Contestado\"; Brasil Escola.","keywords":["Guerra do Contestado","Brasil Escola"],"locations":[],"dates":null},{"text":"Disponível em: https://brasilescola.uol.com.br/historiab/guerra-contestado.htm.","keywords":["https://brasilescola.uol.com.br/historiab/guerra-contestado.htm"],"locations":[],"dates":null},{"text":"Acesso em 28 de maio de 2020.","keywords":["Acesso","maio"],"locations":[],"dates":["2020"]}]}